hdlConvertorAst/__init__.py
hdlConvertorAst/language.py
hdlConvertorAst/parse_hdlConvertor_json.py
hdlConvertorAst/py_ver_compatibility.py
hdlConvertorAst/hdlAst/__init__.py
hdlConvertorAst/hdlAst/_bases.py
hdlConvertorAst/hdlAst/_defs.py
hdlConvertorAst/hdlAst/_expr.py
hdlConvertorAst/hdlAst/_statements.py
hdlConvertorAst/hdlAst/_structural.py
hdlConvertorAst/hdlAst/_typeDefs.py
hdlConvertorAst/hdlAst/utils.py
hdlConvertorAst/to/__init__.py
hdlConvertorAst/to/common.py
hdlConvertorAst/to/hdlUtils.py
hdlConvertorAst/to/hdl_ast_modifier.py
hdlConvertorAst/to/hdl_ast_visitor.py
hdlConvertorAst/to/json.py
hdlConvertorAst/to/json_debug.py
hdlConvertorAst/to/basic_hdl_sim_model/__init__.py
hdlConvertorAst/to/basic_hdl_sim_model/_main.py
hdlConvertorAst/to/basic_hdl_sim_model/expr.py
hdlConvertorAst/to/basic_hdl_sim_model/keywords.py
hdlConvertorAst/to/basic_hdl_sim_model/stm.py
hdlConvertorAst/to/basic_hdl_sim_model/utils.py
hdlConvertorAst/to/hwt/__init__.py
hdlConvertorAst/to/hwt/_main.py
hdlConvertorAst/to/hwt/expr.py
hdlConvertorAst/to/hwt/keywords.py
hdlConvertorAst/to/hwt/stm.py
hdlConvertorAst/to/hwt/utils.py
hdlConvertorAst/to/systemc/__init__.py
hdlConvertorAst/to/systemc/_main.py
hdlConvertorAst/to/systemc/expr.py
hdlConvertorAst/to/systemc/keywords.py
hdlConvertorAst/to/systemc/stm.py
hdlConvertorAst/to/verilog/__init__.py
hdlConvertorAst/to/verilog/constants.py
hdlConvertorAst/to/verilog/expr.py
hdlConvertorAst/to/verilog/keywords.py
hdlConvertorAst/to/verilog/stm.py
hdlConvertorAst/to/verilog/utils.py
hdlConvertorAst/to/verilog/verilog2005.py
hdlConvertorAst/to/vhdl/__init__.py
hdlConvertorAst/to/vhdl/expr.py
hdlConvertorAst/to/vhdl/keywords.py
hdlConvertorAst/to/vhdl/stm.py
hdlConvertorAst/to/vhdl/vhdl2008.py
hdlConvertorAst/translate/__init__.py
hdlConvertorAst/translate/verilog_builtins.py
hdlConvertorAst/translate/vhdl_to_verilog.py
hdlConvertorAst/translate/common/__init__.py
hdlConvertorAst-1.1.dist-info/LICENSE
hdlConvertorAst-1.1.dist-info/METADATA
hdlConvertorAst-1.1.dist-info/WHEEL
hdlConvertorAst-1.1.dist-info/top_level.txt
hdlConvertorAst-1.1.dist-info/RECORD
