Metadata-Version: 2.1
Name: hdlConvertorAst
Version: 1.1
Summary: A library of AST nodes for HDL languages (Verilog, VHDL, ...) and transpiler/compiler utilities
Home-page: https://github.com/Nic30/hdlConvertorAst
Author: Michal Orsak
Author-email: Nic30original@gmail.com
License: MIT
Keywords: hdl,vhdl,verilog,systemverilog,parser,preprocessor,antlr4,ast,code-generator
Platform: UNKNOWN
Classifier: Development Status :: 4 - Beta
Classifier: Intended Audience :: Developers
Classifier: Intended Audience :: Science/Research
Classifier: Operating System :: OS Independent
Classifier: Topic :: Software Development :: Build Tools
Classifier: Programming Language :: Python :: 2.7
Classifier: Programming Language :: Python :: 3
Classifier: Topic :: Scientific/Engineering :: Electronic Design Automation (EDA)
License-File: LICENSE
